traccia_sdk/__init__.py
traccia_sdk/auto.py
traccia_sdk/auto_instrumentation.py
traccia_sdk/cli.py
traccia_sdk/config.py
traccia_sdk/pricing_config.py
traccia_sdk/runtime_config.py
traccia_sdk/context/__init__.py
traccia_sdk/context/context.py
traccia_sdk/context/propagators.py
traccia_sdk/examples/__init__.py
traccia_sdk/exporter/__init__.py
traccia_sdk/exporter/console_exporter.py
traccia_sdk/exporter/http_exporter.py
traccia_sdk/instrumentation/__init__.py
traccia_sdk/instrumentation/anthropic.py
traccia_sdk/instrumentation/decorator.py
traccia_sdk/instrumentation/fastapi.py
traccia_sdk/instrumentation/http_client.py
traccia_sdk/instrumentation/http_server.py
traccia_sdk/instrumentation/openai.py
traccia_sdk/instrumentation/requests.py
traccia_sdk/processors/__init__.py
traccia_sdk/processors/agent_enricher.py
traccia_sdk/processors/batch_processor.py
traccia_sdk/processors/cost_engine.py
traccia_sdk/processors/cost_processor.py
traccia_sdk/processors/drop_policy.py
traccia_sdk/processors/logging_processor.py
traccia_sdk/processors/sampler.py
traccia_sdk/processors/token_counter.py
traccia_sdk/tracer/__init__.py
traccia_sdk/tracer/provider.py
traccia_sdk/tracer/span.py
traccia_sdk/tracer/span_context.py
traccia_sdk/tracer/tracer.py
traccia_sdk-0.1.0.dist-info/METADATA
traccia_sdk-0.1.0.dist-info/WHEEL
traccia_sdk-0.1.0.dist-info/top_level.txt
traccia_sdk-0.1.0.dist-info/RECORD
