Metadata-Version: 2.4
Name: traccia-sdk
Version: 0.1.0
Summary: Tracing SDK for agents
Requires-Python: >=3.9
Requires-Dist: tiktoken>=0.7.0
